
[
  {
    "_id": "integration_whatsapp",
    "platform": "whatsapp",
    "name": "WhatsApp Business",
    "display_name": "WhatsApp Business API",
    "client_id": "wa_client_123456",
    "client_secret": "wa_secret_encrypted",
    "access_token": "wa_access_token_encrypted",
    "refresh_token": "wa_refresh_token_encrypted",
    "scope": ["messages", "contacts", "business_management"],
    "expires_at": 1707955200000,
    "connected_at": 1705276800000,
    "status": "connected",
    "account_id": "1234567890",
    "account_name": "AI SEO+ Business",
    "account_email": "business@aiseo.com",
    "account_avatar": "https://via.placeholder.com/100x100",
    "webhook_url": "https://api.aiseo.com/webhooks/whatsapp",
    "webhook_secret": "wh_secret_123",
    "api_version": "v18.0",
    "rate_limits": {
      "messages_per_second": 80,
      "messages_per_day": 1000,
      "requests_per_hour": 1000
    },
    "sync_enabled": true,
    "sync_frequency": "realtime",
    "last_sync_at": 1705276800000,
    "last_sync_status": "success",
    "error_message": null,
    "metadata": {
      "business_name": "AI SEO+ Business",
      "verified": true,
      "tier": "business",
      "phone_number": "+1-234-567-8900",
      "country": "US"
    },
    "config": {
      "auto_reply": true,
      "message_templates": ["welcome", "order_confirmation", "shipping_update"],
      "webhook_events": ["messages", "message_status", "contacts"]
    },
    "tags": ["business", "primary", "verified"],
    "createdAt": 1705276800000,
    "updatedAt": 1705276800000
  },
  {
    "_id": "integration_facebook",
    "platform": "facebook",
    "name": "Facebook Messenger",
    "display_name": "Facebook Messenger API",
    "client_id": "fb_app_123456789",
    "client_secret": "fb_secret_encrypted",
    "access_token": "fb_access_token_encrypted",
    "refresh_token": "fb_refresh_token_encrypted",
    "scope": ["pages_manage_posts", "pages_read_engagement", "pages_messaging"],
    "expires_at": 1707955200000,
    "connected_at": 1705273200000,
    "status": "connected",
    "account_id": "123456789012345",
    "account_name": "AI SEO+ Business Page",
    "account_email": "business@aiseo.com",
    "account_avatar": "https://via.placeholder.com/100x100",
    "webhook_url": "https://api.aiseo.com/webhooks/facebook",
    "webhook_secret": "fb_webhook_secret",
    "api_version": "v18.0",
    "rate_limits": {
      "messages_per_second": 200,
      "messages_per_day": 10000,
      "requests_per_hour": 200
    },
    "sync_enabled": true,
    "sync_frequency": "realtime",
    "last_sync_at": 1705273200000,
    "last_sync_status": "success",
    "error_message": null,
    "metadata": {
      "page_name": "AI SEO+ Business Page",
      "page_id": "123456789012345",
      "verified": true,
      "followers": 12500
    },
    "config": {
      "auto_reply": true,
      "post_scheduling": true,
      "comment_monitoring": true
    },
    "tags": ["business", "social", "verified"],
    "createdAt": 1705273200000,
    "updatedAt": 1705273200000
  },
  {
    "_id": "integration_instagram",
    "platform": "instagram",
    "name": "Instagram Business",
    "display_name": "Instagram Graph API",
    "client_id": "ig_app_123456789",
    "client_secret": "ig_secret_encrypted",
    "access_token": "ig_access_token_encrypted",
    "refresh_token": "ig_refresh_token_encrypted",
    "scope": ["instagram_basic", "instagram_content_publish", "instagram_manage_messages"],
    "expires_at": 1707955200000,
    "connected_at": 1705269600000,
    "status": "connected",
    "account_id": "instagram_business_123",
    "account_name": "AI SEO+ Instagram",
    "account_email": "business@aiseo.com",
    "account_avatar": "https://via.placeholder.com/100x100",
    "webhook_url": "https://api.aiseo.com/webhooks/instagram",
    "webhook_secret": "ig_webhook_secret",
    "api_version": "v18.0",
    "rate_limits": {
      "posts_per_hour": 25,
      "comments_per_hour": 100,
      "requests_per_hour": 200
    },
    "sync_enabled": true,
    "sync_frequency": "hourly",
    "last_sync_at": 1705269600000,
    "last_sync_status": "success",
    "error_message": null,
    "metadata": {
      "business_account": true,
      "verified": true,
      "followers": 8500,
      "posts_count": 234
    },
    "config": {
      "auto_hashtags": true,
      "story_scheduling": true,
      "dm_auto_reply": true
    },
    "tags": ["business", "visual", "verified"],
    "createdAt": 1705269600000,
    "updatedAt": 1705269600000
  },
  {
    "_id": "integration_twitter",
    "platform": "twitter",
    "name": "Twitter API",
    "display_name": "Twitter API v2",
    "client_id": "tw_app_123456789",
    "client_secret": "tw_secret_encrypted",
    "access_token": "tw_access_token_encrypted",
    "refresh_token": "tw_refresh_token_encrypted",
    "scope": ["read", "write", "dm"],
    "expires_at": 1707955200000,
    "connected_at": 1705266000000,
    "status": "connected",
    "account_id": "twitter_user_123",
    "account_name": "AI SEO+ Twitter",
    "account_email": "business@aiseo.com",
    "account_avatar": "https://via.placeholder.com/100x100",
    "webhook_url": "https://api.aiseo.com/webhooks/twitter",
    "webhook_secret": "tw_webhook_secret",
    "api_version": "v2",
    "rate_limits": {
      "tweets_per_hour": 300,
      "dms_per_hour": 1000,
      "requests_per_15min": 300
    },
    "sync_enabled": true,
    "sync_frequency": "realtime",
    "last_sync_at": 1705266000000,
    "last_sync_status": "success",
    "error_message": null,
    "metadata": {
      "verified": true,
      "followers": 12500,
      "tweets_count": 1234,
      "handle": "@aiseo_official"
    },
    "config": {
      "auto_reply": true,
      "tweet_scheduling": true,
      "mention_monitoring": true
    },
    "tags": ["social", "microblog", "verified"],
    "createdAt": 1705266000000,
    "updatedAt": 1705266000000
  },
  {
    "_id": "integration_linkedin",
    "platform": "linkedin",
    "name": "LinkedIn API",
    "display_name": "LinkedIn API v2",
    "client_id": "li_app_123456789",
    "client_secret": "li_secret_encrypted",
    "access_token": "li_access_token_encrypted",
    "refresh_token": "li_refresh_token_encrypted",
    "scope": ["r_liteprofile", "r_emailaddress", "w_member_social"],
    "expires_at": 1707955200000,
    "connected_at": 1705262400000,
    "status": "connected",
    "account_id": "linkedin_user_123",
    "account_name": "AI SEO+ LinkedIn",
    "account_email": "business@aiseo.com",
    "account_avatar": "https://via.placeholder.com/100x100",
    "webhook_url": "https://api.aiseo.com/webhooks/linkedin",
    "webhook_secret": "li_webhook_secret",
    "api_version": "v2",
    "rate_limits": {
      "posts_per_day": 25,
      "requests_per_day": 500
    },
    "sync_enabled": true,
    "sync_frequency": "daily",
    "last_sync_at": 1705262400000,
    "last_sync_status": "success",
    "error_message": null,
    "metadata": {
      "company_page": true,
      "verified": true,
      "followers": 3500,
      "connections": 1500
    },
    "config": {
      "auto_posting": true,
      "connection_monitoring": true,
      "message_auto_reply": true
    },
    "tags": ["business", "professional", "verified"],
    "createdAt": 1705262400000,
    "updatedAt": 1705262400000
  },
  {
    "_id": "integration_youtube",
    "platform": "youtube",
    "name": "YouTube API",
    "display_name": "YouTube Data API v3",
    "client_id": "yt_app_123456789",
    "client_secret": "yt_secret_encrypted",
    "access_token": "yt_access_token_encrypted",
    "refresh_token": "yt_refresh_token_encrypted",
    "scope": ["https://www.googleapis.com/auth/youtube.readonly", "https://www.googleapis.com/auth/youtube.upload"],
    "expires_at": 1707955200000,
    "connected_at": 1705258800000,
    "status": "connected",
    "account_id": "youtube_channel_123",
    "account_name": "AI SEO+ YouTube",
    "account_email": "business@aiseo.com",
    "account_avatar": "https://via.placeholder.com/100x100",
    "webhook_url": "https://api.aiseo.com/webhooks/youtube",
    "webhook_secret": "yt_webhook_secret",
    "api_version": "v3",
    "rate_limits": {
      "uploads_per_day": 100,
      "requests_per_day": 10000
    },
    "sync_enabled": true,
    "sync_frequency": "daily",
    "last_sync_at": 1705258800000,
    "last_sync_status": "success",
    "error_message": null,
    "metadata": {
      "channel_name": "AI SEO+ Channel",
      "subscribers": 2500,
      "verified": true,
      "total_videos": 123
    },
    "config": {
      "auto_upload": false,
      "comment_monitoring": true,
      "analytics_sync": true
    },
    "tags": ["video", "content", "verified"],
    "createdAt": 1705258800000,
    "updatedAt": 1705258800000
  },
  {
    "_id": "integration_weibo",
    "platform": "weibo",
    "name": "微博开放平台",
    "display_name": "微博开放平台API",
    "client_id": "wb_app_key_123456",
    "client_secret": "wb_secret_encrypted",
    "access_token": "wb_access_token_encrypted",
    "refresh_token": "wb_refresh_token_encrypted",
    "scope": ["all"],
    "expires_at": 1707955200000,
    "connected_at": 1705255200000,
    "status": "connected",
    "account_id": "weibo_user_123456789",
    "account_name": "AI SEO+ 官方微博",
    "account_email": "business@aiseo.com",
    "account_avatar": "https://via.placeholder.com/100x100",
    "webhook_url": "https://api.aiseo.com/webhooks/weibo",
    "webhook_secret": "wb_webhook_secret",
    "api_version": "v2",
    "rate_limits": {
      "posts_per_hour": 150,
      "requests_per_hour": 150
    },
    "sync_enabled": true,
    "sync_frequency": "hourly",
    "last_sync_at": 1705255200000,
    "last_sync_status": "success",
    "error_message": null,
    "metadata": {
      "verified": true,
      "followers": 50000,
      "posts_count": 2345,
      "location": "中国"
    },
    "config": {
      "auto_posting": true,
      "comment_monitoring": true,
      "mention_tracking": true
    },
    "tags": ["social", "china", "verified"],
    "createdAt": 1705255200000,
    "updatedAt": 1705255200000
  },
  {
    "_id": "integration_bilibili",
    "platform": "bilibili",
    "name": "哔哩哔哩开放平台",
    "display_name": "B站开放平台API",
    "client_id": "bili_app_key_123456",
    "client_secret": "bili_secret_encrypted",
    "access_token": "bili_access_token_encrypted",
    "refresh_token": "bili_refresh_token_encrypted",
    "scope": ["video", "user", "dynamic"],
    "expires_at": 1707955200000,
    "connected_at": 1705251600000,
    "status": "connected",
    "account_id": "bili_user_123456789",
    "account_name": "AI SEO+ 官方账号",
    "account_email": "business@aiseo.com",
    "account_avatar": "https://via.placeholder.com/100x100",
    "webhook_url": "https://api.aiseo.com/webhooks/bilibili",
    "webhook_secret": "bili_webhook_secret",
    "api_version": "v3",
    "rate_limits": {
      "videos_per_day": 10,
      "requests_per_hour": 100
    },
    "sync_enabled": true,
    "sync_frequency": "daily",
    "last_sync_at": 1705251600000,
    "last_sync_status": "success",
    "error_message": null,
    "metadata": {
      "verified": true,
      "followers": 15000,
      "videos_count": 89,
      "level": 6
    },
    "config": {
      "auto_upload": false,
      "comment_monitoring": true,
      "danmaku_monitoring": true
    },
    "tags": ["video", "china", "verified"],
    "createdAt": 1705251600000,
    "updatedAt": 1705251600000
  },
  {
    "_id": "integration_douyin",
    "platform": "douyin",
    "name": "抖音开放平台",
    "display_name": "抖音开放平台API",
    "client_id": "dy_app_key_123456",
    "client_secret": "dy_secret_encrypted",
    "access_token": "dy_access_token_encrypted",
    "refresh_token": "dy_refresh_token_encrypted",
    "scope": ["video.data", "user.info", "video.list"],
    "expires_at": 1707955200000,
    "connected_at": 1705248000000,
    "status": "connected",
    "account_id": "douyin_user_123456789",
    "account_name": "AI SEO+ 官方抖音",
    "account_email": "business@aiseo.com",
    "account_avatar": "https://via.placeholder.com/100x100",
    "webhook_url": "https://api.aiseo.com/webhooks/douyin",
    "webhook_secret": "dy_webhook_secret",
    "api_version": "v1",
    "rate_limits": {
      "videos_per_day": 100,
      "requests_per_hour": 1000
    },
    "sync_enabled": true,
    "sync_frequency": "hourly",
    "last_sync_at": 1705248000000,
    "last_sync_status": "success",
    "error_message": null,
    "metadata": {
      "verified": true,
      "followers": 25000,
      "videos_count": 156,
      "likes_count": 500000
    },
    "config": {
      "auto_upload": false,
      "comment_monitoring": true,
      "live_monitoring": true
    },
    "tags": ["video", "china", "short-form", "verified"],
    "createdAt": 1705248000000,
    "updatedAt": 1705248000000
  },
  {
    "_id": "integration_xiaohongshu",
    "platform": "xiaohongshu",
    "name": "小红书开放平台",
    "display_name": "小红书开放平台API",
    "client_id": "xhs_app_key_123456",
    "client_secret": "xhs_secret_encrypted",
    "access_token": "xhs_access_token_encrypted",
    "refresh_token": "xhs_refresh_token_encrypted",
    "scope": ["notes", "user", "comment"],
    "expires_at": 1707955200000,
    "connected_at": 1705244400000,
    "status": "connected",
    "account_id": "xhs_user_123456789",
    "account_name": "AI SEO+ 小红书",
    "account_email": "business@aiseo.com",
    "account_avatar": "https://via.placeholder.com/100x100",
    "webhook_url": "https://api.aiseo.com/webhooks/xiaohongshu",
    "webhook_secret": "xhs_webhook_secret",
    "api_version": "v1",
    "rate_limits": {
      "notes_per_day": 10,
      "requests_per_hour": 100
    },
    "sync_enabled": true,
    "sync_frequency": "daily",
    "last_sync_at": 1705244400000,
    "last_sync_status": "success",
    "error_message": null,
    "metadata": {
      "verified": true,
      "followers": 8000,
      "notes_count": 234,
      "likes_count": 150000
    },
    "config": {
      "auto_posting": false,
      "comment_monitoring": true,
      "note_analytics": true
    },
    "tags": ["lifestyle", "china", "verified"],
    "createdAt": 1705244400000,
    "updatedAt": 1705244400000
  },
  {
    "_id": "integration_kuaishou",
    "platform": "kuaishou",
    "name": "快手开放平台",
    "display_name": "快手开放平台API",
    "client_id": "ks_app_key_123456",
    "client_secret": "ks_secret_encrypted",
    "access_token": "ks_access_token_encrypted",
    "refresh_token": "ks_refresh_token_encrypted",
    "scope": ["user_info", "video_info", "video_upload"],
    "expires_at": 1707955200000,
    "connected_at": 1705240800000,
    "status": "connected",
    "account_id": "ks_user_123456789",
    "account_name": "AI SEO+ 快手官方",
    "account_email": "business@aiseo.com",
    "account_avatar": "https://via.placeholder.com/100x100",
    "webhook_url": "https://api.aiseo.com/webhooks/kuaishou",
    "webhook_secret": "ks_webhook_secret",
    "api_version": "v1",
    "rate_limits": {
      "videos_per_day": 50,
      "requests_per_hour": 500
    },
    "sync_enabled": true,
    "sync_frequency": "daily",
    "last_sync_at": 1705240800000,
    "last_sync_status": "success",
    "error_message": null,
    "metadata": {
      "verified": true,
      "followers": 12000,
      "videos_count": 89,
      "likes_count": 300000
    },
    "config": {
      "auto_upload": false,
      "comment_monitoring": true,
      "live_monitoring": true
    },
    "tags": ["video", "china", "short-form", "verified"],
    "createdAt": 1705240800000,
    "updatedAt": 1705240800000
  },
  {
    "_id": "integration_tiktok",
    "platform": "tiktok",
    "name": "TikTok for Developers",
    "display_name": "TikTok API",
    "client_id": "tt_app_key_123456",
    "client_secret": "tt_secret_encrypted",
    "access_token": "tt_access_token_encrypted",
    "refresh_token": "tt_refresh_token_encrypted",
    "scope": ["user.info.basic", "video.list", "video.upload"],
    "expires_at": 1707955200000,
    "connected_at": 1705237200000,
    "status": "connected",
    "account_id": "tiktok_user_123456789",
    "account_name": "AI SEO+ TikTok",
    "account_email": "business@aiseo.com",
    "account_avatar": "https://via.placeholder.com/100x100",
    "webhook_url": "https://api.aiseo.com/webhooks/tiktok",
    "webhook_secret": "tt_webhook_secret",
    "api_version": "v1",
    "rate_limits": {
      "videos_per_day": 100,
      "requests_per_hour": 1000
    },
    "sync_enabled": true,
    "sync_frequency": "hourly",
    "last_sync_at": 1705237200000,
    "last_sync_status": "success",
    "error_message": null,
    "metadata": {
      "verified": true,
      "followers": 18000,
      "videos_count": 123,
      "likes_count": 450000
    },
    "config": {
      "auto_upload": false,
      "comment_monitoring": true,
      "trend_monitoring": true
    },
    "tags": ["video", "global", "short-form", "verified"],
    "createdAt": 1705237200000,
    "updatedAt": 1705237200000
  }
]
  